{
  "captured_at": "2026-05-12 19:10:32",
  "mode": "kfold",
  "k": 5,
  "total_days": 540,
  "embargo_days": 7,
  "workers": 6,
  "elapsed_s": 25.7,
  "top_symbols_by_tuned_pnl": [
    "AUDUSD",
    "DJ30.r",
    "BTCUSD",
    "GBPJPY",
    "ETHUSD",
    "JPN225ft",
    "XPTUSD.r",
    "SP500.r",
    "GAS-Cr",
    "EURAUD",
    "USOUSD",
    "GBPUSD",
    "GER40.r",
    "UKOUSD",
    "US2000.r",
    "NAS100.r",
    "USDCAD",
    "SPI200.r",
    "EURUSD"
  ],
  "results": {
    "DJ30.r": {
      "params": {
        "min_quality": {
          "trending": 40,
          "ranging": 45,
          "volatile": 40,
          "low_vol": 40
        },
        "sl_atr_mult": 1.0,
        "ratchet_1r": 0.2,
        "ratchet_2r": 0.5
      },
      "folds": [
        {
          "fold_idx": 0,
          "test_window": [
            540.0,
            432.0
          ],
          "embargo_days": 7,
          "train": {
            "trades": 178,
            "wins": 97,
            "pf": 2.21,
            "pnl": 1039.66,
            "wr": 54.5
          },
          "test": null
        },
        {
          "fold_idx": 1,
          "test_window": [
            432.0,
            324.0
          ],
          "embargo_days": 7,
          "train": {
            "trades": 178,
            "wins": 97,
            "pf": 2.21,
            "pnl": 1039.66,
            "wr": 54.5
          },
          "test": null
        },
        {
          "fold_idx": 2,
          "test_window": [
            324.0,
            216.0
          ],
          "embargo_days": 7,
          "train": {
            "trades": 215,
            "wins": 134,
            "pf": 3.07,
            "pnl": 5469.26,
            "wr": 62.3
          },
          "test": {
            "symbol": "DJ30.r",
            "trades": 159,
            "wins": 90,
            "pf": 2.73,
            "wr": 56.6,
            "pnl": 1162.53,
            "pnl_gross": 1162.53,
            "commission_usd": 0.0,
            "swap_usd": 0.0,
            "avg_r": 0.92,
            "avg_peak_r": 2.01,
            "avg_giveback": 1.09,
            "dd": 7.3,
            "equity": 2162.53,
            "cost_flags": {
              "slippage": false,
              "commission": false,
              "swap": false
            }
          }
        },
        {
          "fold_idx": 3,
          "test_window": [
            216.0,
            108.0
          ],
          "embargo_days": 7,
          "train": {
            "trades": 306,
            "wins": 167,
            "pf": 2.03,
            "pnl": 1239.16,
            "wr": 54.6
          },
          "test": {
            "symbol": "DJ30.r",
            "trades": 204,
            "wins": 129,
            "pf": 4.05,
            "wr": 63.2,
            "pnl": 6471.74,
            "pnl_gross": 6471.74,
            "commission_usd": 0.0,
            "swap_usd": 0.0,
            "avg_r": 1.43,
            "avg_peak_r": 2.51,
            "avg_giveback": 1.08,
            "dd": 6.0,
            "equity": 7471.74,
            "cost_flags": {
              "slippage": false,
              "commission": false,
              "swap": false
            }
          }
        },
        {
          "fold_idx": 4,
          "test_window": [
            108.0,
            0.0
          ],
          "embargo_days": 7,
          "train": {
            "trades": 178,
            "wins": 97,
            "pf": 2.21,
            "pnl": 1039.66,
            "wr": 54.5
          },
          "test": {
            "symbol": "DJ30.r",
            "trades": 26,
            "wins": 10,
            "pf": 0.37,
            "wr": 38.5,
            "pnl": -66.69,
            "pnl_gross": -66.69,
            "commission_usd": 0.0,
            "swap_usd": 0.0,
            "avg_r": -0.37,
            "avg_peak_r": 0.84,
            "avg_giveback": 1.31,
            "dd": 8.2,
            "equity": 935.73,
            "cost_flags": {
              "slippage": false,
              "commission": false,
              "swap": false
            }
          }
        }
      ],
      "aggregate": {
        "test_pf_mean": 2.38,
        "test_pf_stdev": 1.52,
        "test_pnl_total": 7567.58,
        "test_pnl_mean": 2522.53,
        "test_trades_total": 389,
        "n_folds": 5
      }
    },
    "JPN225ft": {
      "params": {
        "min_quality": {
          "trending": 45,
          "ranging": 45,
          "volatile": 45,
          "low_vol": 45
        },
        "sl_atr_mult": 1.5,
        "ratchet_1r": 0.2,
        "ratchet_2r": 0.5
      },
      "folds": [
        {
          "fold_idx": 0,
          "test_window": [
            540.0,
            432.0
          ],
          "embargo_days": 7,
          "train": {
            "trades": 233,
            "wins": 152,
            "pf": 2.47,
            "pnl": 1419.46,
            "wr": 65.2
          },
          "test": {
            "symbol": "JPN225ft",
            "trades": 128,
            "wins": 72,
            "pf": 1.33,
            "wr": 56.2,
            "pnl": 168.2,
            "pnl_gross": 168.2,
            "commission_usd": 0.0,
            "swap_usd": 0.0,
            "avg_r": 0.21,
            "avg_peak_r": 1.25,
            "avg_giveback": 1.02,
            "dd": 8.4,
            "equity": 1173.52,
            "cost_flags": {
              "slippage": false,
              "commission": false,
              "swap": false
            }
          }
        },
        {
          "fold_idx": 1,
          "test_window": [
            432.0,
            324.0
          ],
          "embargo_days": 7,
          "train": {
            "trades": 141,
            "wins": 73,
            "pf": 1.21,
            "pnl": 79.63,
            "wr": 51.8
          },
          "test": {
            "symbol": "JPN225ft",
            "trades": 203,
            "wins": 136,
            "pf": 2.34,
            "wr": 67.0,
            "pnl": 1036.66,
            "pnl_gross": 1036.66,
            "commission_usd": 0.0,
            "swap_usd": 0.0,
            "avg_r": 0.46,
            "avg_peak_r": 1.51,
            "avg_giveback": 1.03,
            "dd": 6.5,
            "equity": 2036.66,
            "cost_flags": {
              "slippage": false,
              "commission": false,
              "swap": false
            }
          }
        },
        {
          "fold_idx": 2,
          "test_window": [
            324.0,
            216.0
          ],
          "embargo_days": 7,
          "train": {
            "trades": 181,
            "wins": 110,
            "pf": 1.83,
            "pnl": 511.6,
            "wr": 60.8
          },
          "test": {
            "symbol": "JPN225ft",
            "trades": 26,
            "wins": 10,
            "pf": 0.31,
            "wr": 38.5,
            "pnl": -74.46,
            "pnl_gross": -74.46,
            "commission_usd": 0.0,
            "swap_usd": 0.0,
            "avg_r": -0.39,
            "avg_peak_r": 0.78,
            "avg_giveback": 1.21,
            "dd": 8.5,
            "equity": 930.51,
            "cost_flags": {
              "slippage": false,
              "commission": false,
              "swap": false
            }
          }
        },
        {
          "fold_idx": 3,
          "test_window": [
            216.0,
            108.0
          ],
          "embargo_days": 7,
          "train": {
            "trades": 329,
            "wins": 214,
            "pf": 2.9,
            "pnl": 2615.68,
            "wr": 65.0
          },
          "test": {
            "symbol": "JPN225ft",
            "trades": 74,
            "wins": 56,
            "pf": 3.52,
            "wr": 75.7,
            "pnl": 559.57,
            "pnl_gross": 559.57,
            "commission_usd": 0.0,
            "swap_usd": 0.0,
            "avg_r": 0.84,
            "avg_peak_r": 1.79,
            "avg_giveback": 0.93,
            "dd": 8.2,
            "equity": 1563.34,
            "cost_flags": {
              "slippage": false,
              "commission": false,
              "swap": false
            }
          }
        },
        {
          "fold_idx": 4,
          "test_window": [
            108.0,
            0.0
          ],
          "embargo_days": 7,
          "train": {
            "trades": 128,
            "wins": 72,
            "pf": 1.33,
            "pnl": 168.2,
            "wr": 56.2
          },
          "test": {
            "symbol": "JPN225ft",
            "trades": 239,
            "wins": 178,
            "pf": 4.45,
            "wr": 74.5,
            "pnl": 4303.52,
            "pnl_gross": 4303.52,
            "commission_usd": 0.0,
            "swap_usd": 0.0,
            "avg_r": 1.02,
            "avg_peak_r": 1.97,
            "avg_giveback": 0.93,
            "dd": 5.8,
            "equity": 5303.52,
            "cost_flags": {
              "slippage": false,
              "commission": false,
              "swap": false
            }
          }
        }
      ],
      "aggregate": {
        "test_pf_mean": 2.39,
        "test_pf_stdev": 1.48,
        "test_pnl_total": 5993.49,
        "test_pnl_mean": 1198.7,
        "test_trades_total": 670,
        "n_folds": 5
      }
    },
    "AUDUSD": {
      "params": {
        "min_quality": {
          "trending": 40,
          "ranging": 45,
          "volatile": 40,
          "low_vol": 40
        },
        "sl_atr_mult": 2.0,
        "ratchet_1r": 0.2,
        "ratchet_2r": 0.5
      },
      "folds": [
        {
          "fold_idx": 0,
          "test_window": [
            540.0,
            432.0
          ],
          "embargo_days": 7,
          "train": {
            "trades": 27,
            "wins": 14,
            "pf": 0.21,
            "pnl": -80.32,
            "wr": 51.9
          },
          "test": {
            "symbol": "AUDUSD",
            "trades": 29,
            "wins": 14,
            "pf": 0.14,
            "wr": 48.3,
            "pnl": -81.76,
            "pnl_gross": -81.76,
            "commission_usd": 0.0,
            "swap_usd": 0.0,
            "avg_r": -0.46,
            "avg_peak_r": 0.82,
            "avg_giveback": 1.38,
            "dd": 8.2,
            "equity": 920.14,
            "cost_flags": {
              "slippage": false,
              "commission": false,
              "swap": false
            }
          }
        },
        {
          "fold_idx": 1,
          "test_window": [
            432.0,
            324.0
          ],
          "embargo_days": 7,
          "train": {
            "trades": 156,
            "wins": 107,
            "pf": 0.77,
            "pnl": -104.45,
            "wr": 68.6
          },
          "test": {
            "symbol": "AUDUSD",
            "trades": 51,
            "wins": 34,
            "pf": 0.4,
            "wr": 66.7,
            "pnl": -76.91,
            "pnl_gross": -76.91,
            "commission_usd": 0.0,
            "swap_usd": 0.0,
            "avg_r": -0.18,
            "avg_peak_r": 1.32,
            "avg_giveback": 1.56,
            "dd": 8.4,
            "equity": 927.15,
            "cost_flags": {
              "slippage": false,
              "commission": false,
              "swap": false
            }
          }
        },
        {
          "fold_idx": 2,
          "test_window": [
            324.0,
            216.0
          ],
          "embargo_days": 7,
          "train": {
            "trades": 187,
            "wins": 133,
            "pf": 4.43,
            "pnl": 2168.12,
            "wr": 71.1
          },
          "test": {
            "symbol": "AUDUSD",
            "trades": 164,
            "wins": 117,
            "pf": 1.01,
            "wr": 71.3,
            "pnl": 2.2,
            "pnl_gross": 2.2,
            "commission_usd": 0.0,
            "swap_usd": 0.0,
            "avg_r": 0.02,
            "avg_peak_r": 1.89,
            "avg_giveback": 1.98,
            "dd": 7.6,
            "equity": 1002.2,
            "cost_flags": {
              "slippage": false,
              "commission": false,
              "swap": false
            }
          }
        },
        {
          "fold_idx": 3,
          "test_window": [
            216.0,
            108.0
          ],
          "embargo_days": 7,
          "train": {
            "trades": 61,
            "wins": 30,
            "pf": 0.22,
            "pnl": -148.86,
            "wr": 49.2
          },
          "test": {
            "symbol": "AUDUSD",
            "trades": 141,
            "wins": 108,
            "pf": 5.56,
            "wr": 76.6,
            "pnl": 2279.64,
            "pnl_gross": 2279.64,
            "commission_usd": 0.0,
            "swap_usd": 0.0,
            "avg_r": 1.36,
            "avg_peak_r": 3.11,
            "avg_giveback": 1.86,
            "dd": 8.4,
            "equity": 3294.67,
            "cost_flags": {
              "slippage": false,
              "commission": false,
              "swap": false
            }
          }
        },
        {
          "fold_idx": 4,
          "test_window": [
            108.0,
            0.0
          ],
          "embargo_days": 7,
          "train": {
            "trades": 29,
            "wins": 14,
            "pf": 0.13,
            "pnl": -87.96,
            "wr": 48.3
          },
          "test": {
            "symbol": "AUDUSD",
            "trades": 37,
            "wins": 19,
            "pf": 0.34,
            "wr": 51.4,
            "pnl": -70.31,
            "pnl_gross": -70.31,
            "commission_usd": 0.0,
            "swap_usd": 0.0,
            "avg_r": -0.31,
            "avg_peak_r": 1.73,
            "avg_giveback": 2.29,
            "dd": 8.4,
            "equity": 933.34,
            "cost_flags": {
              "slippage": false,
              "commission": false,
              "swap": false
            }
          }
        }
      ],
      "aggregate": {
        "test_pf_mean": 1.49,
        "test_pf_stdev": 2.06,
        "test_pnl_total": 2052.86,
        "test_pnl_mean": 410.57,
        "test_trades_total": 422,
        "n_folds": 5
      }
    },
    "GBPJPY": {
      "params": {
        "min_quality": {
          "trending": 40,
          "ranging": 45,
          "volatile": 40,
          "low_vol": 40
        },
        "sl_atr_mult": 2.0,
        "ratchet_1r": 0.2,
        "ratchet_2r": 0.5
      },
      "folds": [
        {
          "fold_idx": 0,
          "test_window": [
            540.0,
            432.0
          ],
          "embargo_days": 7,
          "train": {
            "trades": 556,
            "wins": 363,
            "pf": 1.88,
            "pnl": 1490.44,
            "wr": 65.3
          },
          "test": {
            "symbol": "GBPJPY",
            "trades": 53,
            "wins": 31,
            "pf": 0.95,
            "wr": 58.5,
            "pnl": -7.34,
            "pnl_gross": -7.34,
            "commission_usd": 0.0,
            "swap_usd": 0.0,
            "avg_r": 0.05,
            "avg_peak_r": 1.35,
            "avg_giveback": 1.33,
            "dd": 8.1,
            "equity": 994.18,
            "cost_flags": {
              "slippage": false,
              "commission": false,
              "swap": false
            }
          }
        },
        {
          "fold_idx": 1,
          "test_window": [
            432.0,
            324.0
          ],
          "embargo_days": 7,
          "train": {
            "trades": 89,
            "wins": 50,
            "pf": 0.64,
            "pnl": -88.17,
            "wr": 56.2
          },
          "test": {
            "symbol": "GBPJPY",
            "trades": 190,
            "wins": 133,
            "pf": 2.27,
            "wr": 70.0,
            "pnl": 633.31,
            "pnl_gross": 633.31,
            "commission_usd": 0.0,
            "swap_usd": 0.0,
            "avg_r": 0.43,
            "avg_peak_r": 1.6,
            "avg_giveback": 1.18,
            "dd": 4.7,
            "equity": 1633.31,
            "cost_flags": {
              "slippage": false,
              "commission": false,
              "swap": false
            }
          }
        },
        {
          "fold_idx": 2,
          "test_window": [
            324.0,
            216.0
          ],
          "embargo_days": 7,
          "train": {
            "trades": 254,
            "wins": 161,
            "pf": 1.98,
            "pnl": 605.74,
            "wr": 63.4
          },
          "test": {
            "symbol": "GBPJPY",
            "trades": 179,
            "wins": 119,
            "pf": 2.4,
            "wr": 66.5,
            "pnl": 464.88,
            "pnl_gross": 464.88,
            "commission_usd": 0.0,
            "swap_usd": 0.0,
            "avg_r": 0.31,
            "avg_peak_r": 1.44,
            "avg_giveback": 1.12,
            "dd": 6.8,
            "equity": 1464.88,
            "cost_flags": {
              "slippage": false,
              "commission": false,
              "swap": false
            }
          }
        },
        {
          "fold_idx": 3,
          "test_window": [
            216.0,
            108.0
          ],
          "embargo_days": 7,
          "train": {
            "trades": 207,
            "wins": 131,
            "pf": 1.51,
            "pnl": 233.8,
            "wr": 63.3
          },
          "test": {
            "symbol": "GBPJPY",
            "trades": 174,
            "wins": 118,
            "pf": 2.91,
            "wr": 67.8,
            "pnl": 735.27,
            "pnl_gross": 735.27,
            "commission_usd": 0.0,
            "swap_usd": 0.0,
            "avg_r": 0.46,
            "avg_peak_r": 1.77,
            "avg_giveback": 1.34,
            "dd": 7.9,
            "equity": 1735.27,
            "cost_flags": {
              "slippage": false,
              "commission": false,
              "swap": false
            }
          }
        },
        {
          "fold_idx": 4,
          "test_window": [
            108.0,
            0.0
          ],
          "embargo_days": 7,
          "train": {
            "trades": 53,
            "wins": 31,
            "pf": 0.95,
            "pnl": -7.34,
            "wr": 58.5
          },
          "test": {
            "symbol": "GBPJPY",
            "trades": 49,
            "wins": 29,
            "pf": 1.39,
            "wr": 59.2,
            "pnl": 51.86,
            "pnl_gross": 51.86,
            "commission_usd": 0.0,
            "swap_usd": 0.0,
            "avg_r": 0.25,
            "avg_peak_r": 1.34,
            "avg_giveback": 1.07,
            "dd": 8.2,
            "equity": 1053.91,
            "cost_flags": {
              "slippage": false,
              "commission": false,
              "swap": false
            }
          }
        }
      ],
      "aggregate": {
        "test_pf_mean": 1.98,
        "test_pf_stdev": 0.71,
        "test_pnl_total": 1877.98,
        "test_pnl_mean": 375.6,
        "test_trades_total": 645,
        "n_folds": 5
      }
    },
    "XPTUSD.r": {
      "params": {
        "min_quality": {
          "trending": 40,
          "ranging": 45,
          "volatile": 40,
          "low_vol": 40
        },
        "sl_atr_mult": 2.0,
        "ratchet_1r": 0.2,
        "ratchet_2r": 0.5
      },
      "folds": [
        {
          "fold_idx": 0,
          "test_window": [
            540.0,
            432.0
          ],
          "embargo_days": 7,
          "train": {
            "trades": 307,
            "wins": 229,
            "pf": 4.31,
            "pnl": 9691.99,
            "wr": 74.6
          },
          "test": {
            "symbol": "XPTUSD.r",
            "trades": 115,
            "wins": 77,
            "pf": 1.26,
            "wr": 67.0,
            "pnl": 68.06,
            "pnl_gross": 68.06,
            "commission_usd": 0.0,
            "swap_usd": 0.0,
            "avg_r": 0.13,
            "avg_peak_r": 1.2,
            "avg_giveback": 1.07,
            "dd": 4.9,
            "equity": 1068.06,
            "cost_flags": {
              "slippage": false,
              "commission": false,
              "swap": false
            }
          }
        },
        {
          "fold_idx": 1,
          "test_window": [
            432.0,
            324.0
          ],
          "embargo_days": 7,
          "train": {
            "trades": 181,
            "wins": 119,
            "pf": 1.6,
            "pnl": 307.52,
            "wr": 65.7
          },
          "test": {
            "symbol": "XPTUSD.r",
            "trades": 160,
            "wins": 117,
            "pf": 11.04,
            "wr": 73.1,
            "pnl": 4115.24,
            "pnl_gross": 4115.24,
            "commission_usd": 0.0,
            "swap_usd": 0.0,
            "avg_r": 1.24,
            "avg_peak_r": 2.28,
            "avg_giveback": 1.04,
            "dd": 5.0,
            "equity": 5115.24,
            "cost_flags": {
              "slippage": false,
              "commission": false,
              "swap": false
            }
          }
        },
        {
          "fold_idx": 2,
          "test_window": [
            324.0,
            216.0
          ],
          "embargo_days": 7,
          "train": {
            "trades": 551,
            "wins": 399,
            "pf": 2.57,
            "pnl": 4035.33,
            "wr": 72.4
          },
          "test": {
            "symbol": "XPTUSD.r",
            "trades": 97,
            "wins": 65,
            "pf": 2.67,
            "wr": 67.0,
            "pnl": 491.62,
            "pnl_gross": 491.62,
            "commission_usd": 0.0,
            "swap_usd": 0.0,
            "avg_r": 0.62,
            "avg_peak_r": 1.74,
            "avg_giveback": 1.12,
            "dd": 8.1,
            "equity": 1492.64,
            "cost_flags": {
              "slippage": false,
              "commission": false,
              "swap": false
            }
          }
        },
        {
          "fold_idx": 3,
          "test_window": [
            216.0,
            108.0
          ],
          "embargo_days": 7,
          "train": {
            "trades": 334,
            "wins": 246,
            "pf": 2.62,
            "pnl": 1034.26,
            "wr": 73.7
          },
          "test": {
            "symbol": "XPTUSD.r",
            "trades": 190,
            "wins": 146,
            "pf": 5.52,
            "wr": 76.8,
            "pnl": 1981.66,
            "pnl_gross": 1981.66,
            "commission_usd": 0.0,
            "swap_usd": 0.0,
            "avg_r": 0.89,
            "avg_peak_r": 1.94,
            "avg_giveback": 1.05,
            "dd": 5.8,
            "equity": 2981.66,
            "cost_flags": {
              "slippage": false,
              "commission": false,
              "swap": false
            }
          }
        },
        {
          "fold_idx": 4,
          "test_window": [
            108.0,
            0.0
          ],
          "embargo_days": 7,
          "train": {
            "trades": 150,
            "wins": 99,
            "pf": 1.08,
            "pnl": 29.8,
            "wr": 66.0
          },
          "test": {
            "symbol": "XPTUSD.r",
            "trades": 216,
            "wins": 172,
            "pf": 3.83,
            "wr": 79.6,
            "pnl": 1352.12,
            "pnl_gross": 1352.12,
            "commission_usd": 0.0,
            "swap_usd": 0.0,
            "avg_r": 0.65,
            "avg_peak_r": 1.76,
            "avg_giveback": 1.12,
            "dd": 3.4,
            "equity": 2352.12,
            "cost_flags": {
              "slippage": false,
              "commission": false,
              "swap": false
            }
          }
        }
      ],
      "aggregate": {
        "test_pf_mean": 4.86,
        "test_pf_stdev": 3.39,
        "test_pnl_total": 8008.7,
        "test_pnl_mean": 1601.74,
        "test_trades_total": 778,
        "n_folds": 5
      }
    },
    "GAS-Cr": {
      "params": {
        "min_quality": {
          "trending": 40,
          "ranging": 45,
          "volatile": 40,
          "low_vol": 40
        },
        "sl_atr_mult": 2.0,
        "ratchet_1r": 0.2,
        "ratchet_2r": 0.5
      },
      "folds": [
        {
          "fold_idx": 0,
          "test_window": [
            540.0,
            432.0
          ],
          "embargo_days": 7,
          "train": {
            "trades": 73,
            "wins": 46,
            "pf": 1.49,
            "pnl": 109.39,
            "wr": 63.0
          },
          "test": null
        },
        {
          "fold_idx": 1,
          "test_window": [
            432.0,
            324.0
          ],
          "embargo_days": 7,
          "train": {
            "trades": 73,
            "wins": 46,
            "pf": 1.49,
            "pnl": 109.39,
            "wr": 63.0
          },
          "test": null
        },
        {
          "fold_idx": 2,
          "test_window": [
            324.0,
            216.0
          ],
          "embargo_days": 7,
          "train": {
            "trades": 60,
            "wins": 30,
            "pf": 0.63,
            "pnl": -79.51,
            "wr": 50.0
          },
          "test": {
            "symbol": "GAS-Cr",
            "trades": 73,
            "wins": 46,
            "pf": 1.49,
            "wr": 63.0,
            "pnl": 109.39,
            "pnl_gross": 109.39,
            "commission_usd": 0.0,
            "swap_usd": 0.0,
            "avg_r": 0.21,
            "avg_peak_r": 1.52,
            "avg_giveback": 1.36,
            "dd": 8.3,
            "equity": 1112.98,
            "cost_flags": {
              "slippage": false,
              "commission": false,
              "swap": false
            }
          }
        },
        {
          "fold_idx": 3,
          "test_window": [
            216.0,
            108.0
          ],
          "embargo_days": 7,
          "train": {
            "trades": 289,
            "wins": 217,
            "pf": 4.79,
            "pnl": 4396.37,
            "wr": 75.1
          },
          "test": {
            "symbol": "GAS-Cr",
            "trades": 45,
            "wins": 28,
            "pf": 1.59,
            "wr": 62.2,
            "pnl": 94.83,
            "pnl_gross": 94.83,
            "commission_usd": 0.0,
            "swap_usd": 0.0,
            "avg_r": 0.32,
            "avg_peak_r": 1.47,
            "avg_giveback": 1.15,
            "dd": 8.0,
            "equity": 1095.1,
            "cost_flags": {
              "slippage": false,
              "commission": false,
              "swap": false
            }
          }
        },
        {
          "fold_idx": 4,
          "test_window": [
            108.0,
            0.0
          ],
          "embargo_days": 7,
          "train": {
            "trades": 73,
            "wins": 46,
            "pf": 1.49,
            "pnl": 109.39,
            "wr": 63.0
          },
          "test": {
            "symbol": "GAS-Cr",
            "trades": 222,
            "wins": 172,
            "pf": 5.62,
            "wr": 77.5,
            "pnl": 4105.54,
            "pnl_gross": 4105.54,
            "commission_usd": 0.0,
            "swap_usd": 0.0,
            "avg_r": 1.01,
            "avg_peak_r": 2.08,
            "avg_giveback": 1.07,
            "dd": 5.4,
            "equity": 5105.54,
            "cost_flags": {
              "slippage": false,
              "commission": false,
              "swap": false
            }
          }
        }
      ],
      "aggregate": {
        "test_pf_mean": 2.9,
        "test_pf_stdev": 1.92,
        "test_pnl_total": 4309.76,
        "test_pnl_mean": 1436.59,
        "test_trades_total": 340,
        "n_folds": 5
      }
    },
    "BTCUSD": {
      "params": {
        "min_quality": {
          "trending": 40,
          "ranging": 45,
          "volatile": 40,
          "low_vol": 40
        },
        "sl_atr_mult": 1.0,
        "ratchet_1r": 0.3,
        "ratchet_2r": 0.7
      },
      "folds": [
        {
          "fold_idx": 0,
          "test_window": [
            540.0,
            432.0
          ],
          "embargo_days": 7,
          "train": {
            "trades": 965,
            "wins": 570,
            "pf": 2.06,
            "pnl": 5717.03,
            "wr": 59.1
          },
          "test": {
            "symbol": "BTCUSD",
            "trades": 117,
            "wins": 58,
            "pf": 1.0,
            "wr": 49.6,
            "pnl": 0.81,
            "pnl_gross": 0.81,
            "commission_usd": 0.0,
            "swap_usd": 0.0,
            "avg_r": 0.03,
            "avg_peak_r": 1.2,
            "avg_giveback": 1.23,
            "dd": 8.4,
            "equity": 1005.03,
            "cost_flags": {
              "slippage": false,
              "commission": false,
              "swap": false
            }
          }
        },
        {
          "fold_idx": 1,
          "test_window": [
            432.0,
            324.0
          ],
          "embargo_days": 7,
          "train": {
            "trades": 1278,
            "wins": 785,
            "pf": 2.32,
            "pnl": 11039.01,
            "wr": 61.4
          },
          "test": {
            "symbol": "BTCUSD",
            "trades": 356,
            "wins": 214,
            "pf": 2.34,
            "wr": 60.1,
            "pnl": 1062.83,
            "pnl_gross": 1062.83,
            "commission_usd": 0.0,
            "swap_usd": 0.0,
            "avg_r": 0.57,
            "avg_peak_r": 1.76,
            "avg_giveback": 1.24,
            "dd": 5.2,
            "equity": 2062.83,
            "cost_flags": {
              "slippage": false,
              "commission": false,
              "swap": false
            }
          }
        },
        {
          "fold_idx": 2,
          "test_window": [
            324.0,
            216.0
          ],
          "embargo_days": 7,
          "train": {
            "trades": 887,
            "wins": 547,
            "pf": 2.28,
            "pnl": 4416.17,
            "wr": 61.7
          },
          "test": {
            "symbol": "BTCUSD",
            "trades": 365,
            "wins": 225,
            "pf": 2.51,
            "wr": 61.6,
            "pnl": 1324.26,
            "pnl_gross": 1324.26,
            "commission_usd": 0.0,
            "swap_usd": 0.0,
            "avg_r": 0.71,
            "avg_peak_r": 1.88,
            "avg_giveback": 1.2,
            "dd": 6.3,
            "equity": 2324.26,
            "cost_flags": {
              "slippage": false,
              "commission": false,
              "swap": false
            }
          }
        },
        {
          "fold_idx": 3,
          "test_window": [
            216.0,
            108.0
          ],
          "embargo_days": 7,
          "train": {
            "trades": 470,
            "wins": 280,
            "pf": 1.83,
            "pnl": 719.0,
            "wr": 59.6
          },
          "test": {
            "symbol": "BTCUSD",
            "trades": 339,
            "wins": 195,
            "pf": 2.21,
            "wr": 57.5,
            "pnl": 807.04,
            "pnl_gross": 807.04,
            "commission_usd": 0.0,
            "swap_usd": 0.0,
            "avg_r": 0.47,
            "avg_peak_r": 1.68,
            "avg_giveback": 1.27,
            "dd": 7.7,
            "equity": 1807.04,
            "cost_flags": {
              "slippage": false,
              "commission": false,
              "swap": false
            }
          }
        },
        {
          "fold_idx": 4,
          "test_window": [
            108.0,
            0.0
          ],
          "embargo_days": 7,
          "train": {
            "trades": 1308,
            "wins": 751,
            "pf": 1.93,
            "pnl": 5932.07,
            "wr": 57.4
          },
          "test": {
            "symbol": "BTCUSD",
            "trades": 413,
            "wins": 270,
            "pf": 2.28,
            "wr": 65.4,
            "pnl": 1152.54,
            "pnl_gross": 1152.54,
            "commission_usd": 0.0,
            "swap_usd": 0.0,
            "avg_r": 0.6,
            "avg_peak_r": 1.8,
            "avg_giveback": 1.24,
            "dd": 5.3,
            "equity": 2152.54,
            "cost_flags": {
              "slippage": false,
              "commission": false,
              "swap": false
            }
          }
        }
      ],
      "aggregate": {
        "test_pf_mean": 2.07,
        "test_pf_stdev": 0.54,
        "test_pnl_total": 4347.48,
        "test_pnl_mean": 869.5,
        "test_trades_total": 1590,
        "n_folds": 5
      }
    },
    "ETHUSD": {
      "params": {
        "min_quality": {
          "trending": 40,
          "ranging": 45,
          "volatile": 40,
          "low_vol": 40
        },
        "sl_atr_mult": 2.0,
        "ratchet_1r": 0.3,
        "ratchet_2r": 0.7
      },
      "folds": [
        {
          "fold_idx": 0,
          "test_window": [
            540.0,
            432.0
          ],
          "embargo_days": 7,
          "train": {
            "trades": 1500,
            "wins": 1180,
            "pf": 3.53,
            "pnl": 895943.51,
            "wr": 78.7
          },
          "test": {
            "symbol": "ETHUSD",
            "trades": 346,
            "wins": 258,
            "pf": 5.6,
            "wr": 74.6,
            "pnl": 3000.67,
            "pnl_gross": 3000.67,
            "commission_usd": 0.0,
            "swap_usd": 0.0,
            "avg_r": 0.91,
            "avg_peak_r": 2.02,
            "avg_giveback": 1.11,
            "dd": 3.8,
            "equity": 4000.67,
            "cost_flags": {
              "slippage": false,
              "commission": false,
              "swap": false
            }
          }
        },
        {
          "fold_idx": 1,
          "test_window": [
            432.0,
            324.0
          ],
          "embargo_days": 7,
          "train": {
            "trades": 1422,
            "wins": 1104,
            "pf": 4.26,
            "pnl": 204140.6,
            "wr": 77.6
          },
          "test": {
            "symbol": "ETHUSD",
            "trades": 377,
            "wins": 289,
            "pf": 5.82,
            "wr": 76.7,
            "pnl": 4092.78,
            "pnl_gross": 4092.78,
            "commission_usd": 0.0,
            "swap_usd": 0.0,
            "avg_r": 1.06,
            "avg_peak_r": 2.11,
            "avg_giveback": 1.06,
            "dd": 3.7,
            "equity": 5092.78,
            "cost_flags": {
              "slippage": false,
              "commission": false,
              "swap": false
            }
          }
        },
        {
          "fold_idx": 2,
          "test_window": [
            324.0,
            216.0
          ],
          "embargo_days": 7,
          "train": {
            "trades": 1346,
            "wins": 1026,
            "pf": 4.72,
            "pnl": 29655.87,
            "wr": 76.2
          },
          "test": {
            "symbol": "ETHUSD",
            "trades": 450,
            "wins": 374,
            "pf": 8.98,
            "wr": 83.1,
            "pnl": 24492.34,
            "pnl_gross": 24492.34,
            "commission_usd": 0.0,
            "swap_usd": 0.0,
            "avg_r": 1.56,
            "avg_peak_r": 2.59,
            "avg_giveback": 1.02,
            "dd": 6.8,
            "equity": 25492.34,
            "cost_flags": {
              "slippage": false,
              "commission": false,
              "swap": false
            }
          }
        },
        {
          "fold_idx": 3,
          "test_window": [
            216.0,
            108.0
          ],
          "embargo_days": 7,
          "train": {
            "trades": 1360,
            "wins": 1027,
            "pf": 6.53,
            "pnl": 187818.63,
            "wr": 75.5
          },
          "test": {
            "symbol": "ETHUSD",
            "trades": 282,
            "wins": 214,
            "pf": 5.4,
            "wr": 75.9,
            "pnl": 1915.34,
            "pnl_gross": 1915.34,
            "commission_usd": 0.0,
            "swap_usd": 0.0,
            "avg_r": 0.93,
            "avg_peak_r": 2.05,
            "avg_giveback": 1.13,
            "dd": 3.9,
            "equity": 2915.34,
            "cost_flags": {
              "slippage": false,
              "commission": false,
              "swap": false
            }
          }
        },
        {
          "fold_idx": 4,
          "test_window": [
            108.0,
            0.0
          ],
          "embargo_days": 7,
          "train": {
            "trades": 1409,
            "wins": 1081,
            "pf": 5.71,
            "pnl": 318675.56,
            "wr": 76.7
          },
          "test": {
            "symbol": "ETHUSD",
            "trades": 362,
            "wins": 277,
            "pf": 3.02,
            "wr": 76.5,
            "pnl": 1734.41,
            "pnl_gross": 1734.41,
            "commission_usd": 0.0,
            "swap_usd": 0.0,
            "avg_r": 0.75,
            "avg_peak_r": 1.89,
            "avg_giveback": 1.14,
            "dd": 7.1,
            "equity": 2734.41,
            "cost_flags": {
              "slippage": false,
              "commission": false,
              "swap": false
            }
          }
        }
      ],
      "aggregate": {
        "test_pf_mean": 5.76,
        "test_pf_stdev": 1.9,
        "test_pnl_total": 35235.54,
        "test_pnl_mean": 7047.11,
        "test_trades_total": 1817,
        "n_folds": 5
      }
    },
    "SP500.r": {
      "params": {
        "min_quality": {
          "trending": 40,
          "ranging": 45,
          "volatile": 40,
          "low_vol": 40
        },
        "sl_atr_mult": 2.0,
        "ratchet_1r": 0.2,
        "ratchet_2r": 0.5
      },
      "folds": [
        {
          "fold_idx": 0,
          "test_window": [
            540.0,
            432.0
          ],
          "embargo_days": 7,
          "train": {
            "trades": 83,
            "wins": 52,
            "pf": 3.3,
            "pnl": 709.67,
            "wr": 62.7
          },
          "test": {
            "symbol": "SP500.r",
            "trades": 197,
            "wins": 135,
            "pf": 1.65,
            "wr": 68.5,
            "pnl": 374.51,
            "pnl_gross": 374.51,
            "commission_usd": 0.0,
            "swap_usd": 0.0,
            "avg_r": 0.32,
            "avg_peak_r": 1.34,
            "avg_giveback": 1.01,
            "dd": 6.3,
            "equity": 1374.51,
            "cost_flags": {
              "slippage": false,
              "commission": false,
              "swap": false
            }
          }
        },
        {
          "fold_idx": 1,
          "test_window": [
            432.0,
            324.0
          ],
          "embargo_days": 7,
          "train": {
            "trades": 473,
            "wins": 327,
            "pf": 2.34,
            "pnl": 2255.25,
            "wr": 69.1
          },
          "test": {
            "symbol": "SP500.r",
            "trades": 90,
            "wins": 55,
            "pf": 3.33,
            "wr": 61.1,
            "pnl": 801.75,
            "pnl_gross": 801.75,
            "commission_usd": 0.0,
            "swap_usd": 0.0,
            "avg_r": 0.78,
            "avg_peak_r": 1.76,
            "avg_giveback": 0.94,
            "dd": 8.1,
            "equity": 1803.25,
            "cost_flags": {
              "slippage": false,
              "commission": false,
              "swap": false
            }
          }
        },
        {
          "fold_idx": 2,
          "test_window": [
            324.0,
            216.0
          ],
          "embargo_days": 7,
          "train": {
            "trades": 528,
            "wins": 359,
            "pf": 2.44,
            "pnl": 3229.58,
            "wr": 68.0
          },
          "test": {
            "symbol": "SP500.r",
            "trades": 215,
            "wins": 153,
            "pf": 2.4,
            "wr": 71.2,
            "pnl": 988.35,
            "pnl_gross": 988.35,
            "commission_usd": 0.0,
            "swap_usd": 0.0,
            "avg_r": 0.57,
            "avg_peak_r": 1.51,
            "avg_giveback": 0.91,
            "dd": 4.0,
            "equity": 1988.35,
            "cost_flags": {
              "slippage": false,
              "commission": false,
              "swap": false
            }
          }
        },
        {
          "fold_idx": 3,
          "test_window": [
            216.0,
            108.0
          ],
          "embargo_days": 7,
          "train": {
            "trades": 541,
            "wins": 392,
            "pf": 4.09,
            "pnl": 5335.65,
            "wr": 72.5
          },
          "test": {
            "symbol": "SP500.r",
            "trades": 77,
            "wins": 51,
            "pf": 2.88,
            "wr": 66.2,
            "pnl": 467.78,
            "pnl_gross": 467.78,
            "commission_usd": 0.0,
            "swap_usd": 0.0,
            "avg_r": 0.68,
            "avg_peak_r": 1.67,
            "avg_giveback": 0.97,
            "dd": 8.1,
            "equity": 1468.89,
            "cost_flags": {
              "slippage": false,
              "commission": false,
              "swap": false
            }
          }
        },
        {
          "fold_idx": 4,
          "test_window": [
            108.0,
            0.0
          ],
          "embargo_days": 7,
          "train": {
            "trades": 322,
            "wins": 221,
            "pf": 2.5,
            "pnl": 1770.36,
            "wr": 68.6
          },
          "test": {
            "symbol": "SP500.r",
            "trades": 237,
            "wins": 184,
            "pf": 6.13,
            "wr": 77.6,
            "pnl": 3473.58,
            "pnl_gross": 3473.58,
            "commission_usd": 0.0,
            "swap_usd": 0.0,
            "avg_r": 0.84,
            "avg_peak_r": 1.81,
            "avg_giveback": 0.96,
            "dd": 5.9,
            "equity": 4473.58,
            "cost_flags": {
              "slippage": false,
              "commission": false,
              "swap": false
            }
          }
        }
      ],
      "aggregate": {
        "test_pf_mean": 3.28,
        "test_pf_stdev": 1.53,
        "test_pnl_total": 6105.97,
        "test_pnl_mean": 1221.19,
        "test_trades_total": 816,
        "n_folds": 5
      }
    },
    "USOUSD": {
      "params": {
        "min_quality": {
          "trending": 45,
          "ranging": 45,
          "volatile": 45,
          "low_vol": 45
        },
        "sl_atr_mult": 2.0,
        "ratchet_1r": 0.2,
        "ratchet_2r": 0.5
      },
      "folds": [
        {
          "fold_idx": 0,
          "test_window": [
            540.0,
            432.0
          ],
          "embargo_days": 7,
          "train": {
            "trades": 70,
            "wins": 45,
            "pf": 0.93,
            "pnl": -16.75,
            "wr": 64.3
          },
          "test": null
        },
        {
          "fold_idx": 1,
          "test_window": [
            432.0,
            324.0
          ],
          "embargo_days": 7,
          "train": {
            "trades": 70,
            "wins": 45,
            "pf": 0.93,
            "pnl": -16.75,
            "wr": 64.3
          },
          "test": null
        },
        {
          "fold_idx": 2,
          "test_window": [
            324.0,
            216.0
          ],
          "embargo_days": 7,
          "train": {
            "trades": 98,
            "wins": 60,
            "pf": 1.89,
            "pnl": 334.21,
            "wr": 61.2
          },
          "test": {
            "symbol": "USOUSD",
            "trades": 62,
            "wins": 39,
            "pf": 0.95,
            "wr": 62.9,
            "pnl": -10.47,
            "pnl_gross": -10.47,
            "commission_usd": 0.0,
            "swap_usd": 0.0,
            "avg_r": 0.07,
            "avg_peak_r": 1.26,
            "avg_giveback": 1.22,
            "dd": 8.0,
            "equity": 989.93,
            "cost_flags": {
              "slippage": false,
              "commission": false,
              "swap": false
            }
          }
        },
        {
          "fold_idx": 3,
          "test_window": [
            216.0,
            108.0
          ],
          "embargo_days": 7,
          "train": {
            "trades": 98,
            "wins": 62,
            "pf": 0.98,
            "pnl": -4.55,
            "wr": 63.3
          },
          "test": {
            "symbol": "USOUSD",
            "trades": 113,
            "wins": 73,
            "pf": 2.49,
            "wr": 64.6,
            "pnl": 822.57,
            "pnl_gross": 822.57,
            "commission_usd": 0.0,
            "swap_usd": 0.0,
            "avg_r": 0.8,
            "avg_peak_r": 2.0,
            "avg_giveback": 1.22,
            "dd": 8.8,
            "equity": 1838.66,
            "cost_flags": {
              "slippage": false,
              "commission": false,
              "swap": false
            }
          }
        },
        {
          "fold_idx": 4,
          "test_window": [
            108.0,
            0.0
          ],
          "embargo_days": 7,
          "train": {
            "trades": 70,
            "wins": 45,
            "pf": 0.93,
            "pnl": -16.75,
            "wr": 64.3
          },
          "test": {
            "symbol": "USOUSD",
            "trades": 40,
            "wins": 25,
            "pf": 2.0,
            "wr": 62.5,
            "pnl": 148.58,
            "pnl_gross": 148.58,
            "commission_usd": 0.0,
            "swap_usd": 0.0,
            "avg_r": 0.45,
            "avg_peak_r": 1.6,
            "avg_giveback": 1.17,
            "dd": 8.3,
            "equity": 1152.16,
            "cost_flags": {
              "slippage": false,
              "commission": false,
              "swap": false
            }
          }
        }
      ],
      "aggregate": {
        "test_pf_mean": 1.81,
        "test_pf_stdev": 0.64,
        "test_pnl_total": 960.68,
        "test_pnl_mean": 320.23,
        "test_trades_total": 215,
        "n_folds": 5
      }
    },
    "EURAUD": {
      "params": {
        "min_quality": {
          "trending": 40,
          "ranging": 45,
          "volatile": 40,
          "low_vol": 40
        },
        "sl_atr_mult": 2.5,
        "ratchet_1r": 0.3,
        "ratchet_2r": 0.7
      },
      "folds": [
        {
          "fold_idx": 0,
          "test_window": [
            540.0,
            432.0
          ],
          "embargo_days": 7,
          "train": {
            "trades": 646,
            "wins": 534,
            "pf": 5.51,
            "pnl": 17764.73,
            "wr": 82.7
          },
          "test": {
            "symbol": "EURAUD",
            "trades": 85,
            "wins": 61,
            "pf": 2.39,
            "wr": 71.8,
            "pnl": 214.45,
            "pnl_gross": 214.45,
            "commission_usd": 0.0,
            "swap_usd": 0.0,
            "avg_r": 0.38,
            "avg_peak_r": 1.46,
            "avg_giveback": 1.08,
            "dd": 7.2,
            "equity": 1214.45,
            "cost_flags": {
              "slippage": false,
              "commission": false,
              "swap": false
            }
          }
        },
        {
          "fold_idx": 1,
          "test_window": [
            432.0,
            324.0
          ],
          "embargo_days": 7,
          "train": {
            "trades": 728,
            "wins": 602,
            "pf": 5.39,
            "pnl": 24614.12,
            "wr": 82.7
          },
          "test": {
            "symbol": "EURAUD",
            "trades": 82,
            "wins": 61,
            "pf": 1.52,
            "wr": 74.4,
            "pnl": 80.02,
            "pnl_gross": 80.02,
            "commission_usd": 0.0,
            "swap_usd": 0.0,
            "avg_r": 0.23,
            "avg_peak_r": 1.34,
            "avg_giveback": 1.11,
            "dd": 3.6,
            "equity": 1080.02,
            "cost_flags": {
              "slippage": false,
              "commission": false,
              "swap": false
            }
          }
        },
        {
          "fold_idx": 2,
          "test_window": [
            324.0,
            216.0
          ],
          "embargo_days": 7,
          "train": {
            "trades": 629,
            "wins": 521,
            "pf": 4.93,
            "pnl": 13675.47,
            "wr": 82.8
          },
          "test": {
            "symbol": "EURAUD",
            "trades": 109,
            "wins": 82,
            "pf": 2.3,
            "wr": 75.2,
            "pnl": 271.79,
            "pnl_gross": 271.79,
            "commission_usd": 0.0,
            "swap_usd": 0.0,
            "avg_r": 0.44,
            "avg_peak_r": 1.59,
            "avg_giveback": 1.15,
            "dd": 5.6,
            "equity": 1271.79,
            "cost_flags": {
              "slippage": false,
              "commission": false,
              "swap": false
            }
          }
        },
        {
          "fold_idx": 3,
          "test_window": [
            216.0,
            108.0
          ],
          "embargo_days": 7,
          "train": {
            "trades": 449,
            "wins": 353,
            "pf": 3.74,
            "pnl": 2762.97,
            "wr": 78.6
          },
          "test": {
            "symbol": "EURAUD",
            "trades": 198,
            "wins": 173,
            "pf": 10.17,
            "wr": 87.4,
            "pnl": 2784.94,
            "pnl_gross": 2784.94,
            "commission_usd": 0.0,
            "swap_usd": 0.0,
            "avg_r": 1.08,
            "avg_peak_r": 2.09,
            "avg_giveback": 1.0,
            "dd": 4.2,
            "equity": 3784.94,
            "cost_flags": {
              "slippage": false,
              "commission": false,
              "swap": false
            }
          }
        },
        {
          "fold_idx": 4,
          "test_window": [
            108.0,
            0.0
          ],
          "embargo_days": 7,
          "train": {
            "trades": 442,
            "wins": 346,
            "pf": 4.34,
            "pnl": 3717.56,
            "wr": 78.3
          },
          "test": {
            "symbol": "EURAUD",
            "trades": 223,
            "wins": 190,
            "pf": 5.61,
            "wr": 85.2,
            "pnl": 2403.45,
            "pnl_gross": 2403.45,
            "commission_usd": 0.0,
            "swap_usd": 0.0,
            "avg_r": 0.97,
            "avg_peak_r": 2.03,
            "avg_giveback": 1.06,
            "dd": 3.9,
            "equity": 3403.45,
            "cost_flags": {
              "slippage": false,
              "commission": false,
              "swap": false
            }
          }
        }
      ],
      "aggregate": {
        "test_pf_mean": 4.4,
        "test_pf_stdev": 3.21,
        "test_pnl_total": 5754.65,
        "test_pnl_mean": 1150.93,
        "test_trades_total": 697,
        "n_folds": 5
      }
    },
    "UKOUSD": {
      "params": {
        "min_quality": {
          "trending": 40,
          "ranging": 45,
          "volatile": 40,
          "low_vol": 40
        },
        "sl_atr_mult": 2.5,
        "ratchet_1r": 0.2,
        "ratchet_2r": 0.5
      },
      "folds": [
        {
          "fold_idx": 0,
          "test_window": [
            540.0,
            432.0
          ],
          "embargo_days": 7,
          "train": {
            "trades": 271,
            "wins": 189,
            "pf": 2.51,
            "pnl": 2264.07,
            "wr": 69.7
          },
          "test": {
            "symbol": "UKOUSD",
            "trades": 91,
            "wins": 58,
            "pf": 1.46,
            "wr": 63.7,
            "pnl": 126.1,
            "pnl_gross": 126.1,
            "commission_usd": 0.0,
            "swap_usd": 0.0,
            "avg_r": 0.1,
            "avg_peak_r": 1.22,
            "avg_giveback": 1.14,
            "dd": 7.8,
            "equity": 1126.1,
            "cost_flags": {
              "slippage": false,
              "commission": false,
              "swap": false
            }
          }
        },
        {
          "fold_idx": 1,
          "test_window": [
            432.0,
            324.0
          ],
          "embargo_days": 7,
          "train": {
            "trades": 231,
            "wins": 153,
            "pf": 1.55,
            "pnl": 373.53,
            "wr": 66.2
          },
          "test": {
            "symbol": "UKOUSD",
            "trades": 106,
            "wins": 73,
            "pf": 2.85,
            "wr": 68.9,
            "pnl": 685.42,
            "pnl_gross": 685.42,
            "commission_usd": 0.0,
            "swap_usd": 0.0,
            "avg_r": 0.58,
            "avg_peak_r": 1.75,
            "avg_giveback": 1.19,
            "dd": 8.2,
            "equity": 1688.85,
            "cost_flags": {
              "slippage": false,
              "commission": false,
              "swap": false
            }
          }
        },
        {
          "fold_idx": 2,
          "test_window": [
            324.0,
            216.0
          ],
          "embargo_days": 7,
          "train": {
            "trades": 239,
            "wins": 158,
            "pf": 2.21,
            "pnl": 1030.61,
            "wr": 66.1
          },
          "test": {
            "symbol": "UKOUSD",
            "trades": 82,
            "wins": 51,
            "pf": 0.96,
            "wr": 62.2,
            "pnl": -10.01,
            "pnl_gross": -10.01,
            "commission_usd": 0.0,
            "swap_usd": 0.0,
            "avg_r": 0.03,
            "avg_peak_r": 1.27,
            "avg_giveback": 1.28,
            "dd": 6.0,
            "equity": 989.99,
            "cost_flags": {
              "slippage": false,
              "commission": false,
              "swap": false
            }
          }
        },
        {
          "fold_idx": 3,
          "test_window": [
            216.0,
            108.0
          ],
          "embargo_days": 7,
          "train": {
            "trades": 326,
            "wins": 230,
            "pf": 3.73,
            "pnl": 3729.59,
            "wr": 70.6
          },
          "test": {
            "symbol": "UKOUSD",
            "trades": 46,
            "wins": 32,
            "pf": 1.67,
            "wr": 69.6,
            "pnl": 98.89,
            "pnl_gross": 98.89,
            "commission_usd": 0.0,
            "swap_usd": 0.0,
            "avg_r": 0.32,
            "avg_peak_r": 1.61,
            "avg_giveback": 1.33,
            "dd": 8.2,
            "equity": 1100.84,
            "cost_flags": {
              "slippage": false,
              "commission": false,
              "swap": false
            }
          }
        },
        {
          "fold_idx": 4,
          "test_window": [
            108.0,
            0.0
          ],
          "embargo_days": 7,
          "train": {
            "trades": 76,
            "wins": 46,
            "pf": 1.35,
            "pnl": 87.19,
            "wr": 60.5
          },
          "test": {
            "symbol": "UKOUSD",
            "trades": 130,
            "wins": 99,
            "pf": 6.11,
            "wr": 76.2,
            "pnl": 3107.61,
            "pnl_gross": 3107.61,
            "commission_usd": 0.0,
            "swap_usd": 0.0,
            "avg_r": 1.17,
            "avg_peak_r": 2.34,
            "avg_giveback": 1.19,
            "dd": 4.6,
            "equity": 4107.61,
            "cost_flags": {
              "slippage": false,
              "commission": false,
              "swap": false
            }
          }
        }
      ],
      "aggregate": {
        "test_pf_mean": 2.61,
        "test_pf_stdev": 1.86,
        "test_pnl_total": 4008.01,
        "test_pnl_mean": 801.6,
        "test_trades_total": 455,
        "n_folds": 5
      }
    },
    "GBPUSD": {
      "params": {
        "min_quality": {
          "trending": 40,
          "ranging": 45,
          "volatile": 40,
          "low_vol": 40
        },
        "sl_atr_mult": 2.5,
        "ratchet_1r": 0.2,
        "ratchet_2r": 0.5
      },
      "folds": [
        {
          "fold_idx": 0,
          "test_window": [
            540.0,
            432.0
          ],
          "embargo_days": 7,
          "train": {
            "trades": 25,
            "wins": 10,
            "pf": 0.26,
            "pnl": -84.34,
            "wr": 40.0
          },
          "test": {
            "symbol": "GBPUSD",
            "trades": 106,
            "wins": 75,
            "pf": 3.2,
            "wr": 70.8,
            "pnl": 596.99,
            "pnl_gross": 596.99,
            "commission_usd": 0.0,
            "swap_usd": 0.0,
            "avg_r": 0.74,
            "avg_peak_r": 1.92,
            "avg_giveback": 1.2,
            "dd": 5.4,
            "equity": 1596.99,
            "cost_flags": {
              "slippage": false,
              "commission": false,
              "swap": false
            }
          }
        },
        {
          "fold_idx": 1,
          "test_window": [
            432.0,
            324.0
          ],
          "embargo_days": 7,
          "train": {
            "trades": 610,
            "wins": 476,
            "pf": 2.95,
            "pnl": 9113.84,
            "wr": 78.0
          },
          "test": {
            "symbol": "GBPUSD",
            "trades": 22,
            "wins": 7,
            "pf": 0.25,
            "wr": 31.8,
            "pnl": -79.7,
            "pnl_gross": -79.7,
            "commission_usd": 0.0,
            "swap_usd": 0.0,
            "avg_r": -0.47,
            "avg_peak_r": 0.79,
            "avg_giveback": 1.33,
            "dd": 8.0,
            "equity": 920.45,
            "cost_flags": {
              "slippage": false,
              "commission": false,
              "swap": false
            }
          }
        },
        {
          "fold_idx": 2,
          "test_window": [
            324.0,
            216.0
          ],
          "embargo_days": 7,
          "train": {
            "trades": 336,
            "wins": 246,
            "pf": 2.67,
            "pnl": 1634.44,
            "wr": 73.2
          },
          "test": {
            "symbol": "GBPUSD",
            "trades": 146,
            "wins": 119,
            "pf": 6.05,
            "wr": 81.5,
            "pnl": 2106.92,
            "pnl_gross": 2106.92,
            "commission_usd": 0.0,
            "swap_usd": 0.0,
            "avg_r": 1.17,
            "avg_peak_r": 2.31,
            "avg_giveback": 1.15,
            "dd": 4.9,
            "equity": 3106.92,
            "cost_flags": {
              "slippage": false,
              "commission": false,
              "swap": false
            }
          }
        },
        {
          "fold_idx": 3,
          "test_window": [
            216.0,
            108.0
          ],
          "embargo_days": 7,
          "train": {
            "trades": 273,
            "wins": 200,
            "pf": 2.4,
            "pnl": 1001.46,
            "wr": 73.3
          },
          "test": {
            "symbol": "GBPUSD",
            "trades": 121,
            "wins": 91,
            "pf": 2.91,
            "wr": 75.2,
            "pnl": 618.34,
            "pnl_gross": 618.34,
            "commission_usd": 0.0,
            "swap_usd": 0.0,
            "avg_r": 0.6,
            "avg_peak_r": 1.74,
            "avg_giveback": 1.15,
            "dd": 6.3,
            "equity": 1618.34,
            "cost_flags": {
              "slippage": false,
              "commission": false,
              "swap": false
            }
          }
        },
        {
          "fold_idx": 4,
          "test_window": [
            108.0,
            0.0
          ],
          "embargo_days": 7,
          "train": {
            "trades": 114,
            "wins": 77,
            "pf": 2.6,
            "pnl": 538.6,
            "wr": 67.5
          },
          "test": {
            "symbol": "GBPUSD",
            "trades": 175,
            "wins": 137,
            "pf": 2.28,
            "wr": 78.3,
            "pnl": 516.29,
            "pnl_gross": 516.29,
            "commission_usd": 0.0,
            "swap_usd": 0.0,
            "avg_r": 0.44,
            "avg_peak_r": 1.58,
            "avg_giveback": 1.15,
            "dd": 6.4,
            "equity": 1516.29,
            "cost_flags": {
              "slippage": false,
              "commission": false,
              "swap": false
            }
          }
        }
      ],
      "aggregate": {
        "test_pf_mean": 2.94,
        "test_pf_stdev": 1.87,
        "test_pnl_total": 3758.84,
        "test_pnl_mean": 751.77,
        "test_trades_total": 570,
        "n_folds": 5
      }
    },
    "GER40.r": {
      "params": {
        "min_quality": {
          "trending": 40,
          "ranging": 45,
          "volatile": 40,
          "low_vol": 40
        },
        "sl_atr_mult": 2.0,
        "ratchet_1r": 0.3,
        "ratchet_2r": 0.7
      },
      "folds": [
        {
          "fold_idx": 0,
          "test_window": [
            540.0,
            432.0
          ],
          "embargo_days": 7,
          "train": {
            "trades": 875,
            "wins": 642,
            "pf": 2.61,
            "pnl": 30309.65,
            "wr": 73.4
          },
          "test": {
            "symbol": "GER40.r",
            "trades": 359,
            "wins": 318,
            "pf": 7.47,
            "wr": 88.6,
            "pnl": 43000.03,
            "pnl_gross": 43000.03,
            "commission_usd": 0.0,
            "swap_usd": 0.0,
            "avg_r": 1.56,
            "avg_peak_r": 2.68,
            "avg_giveback": 1.12,
            "dd": 7.0,
            "equity": 44000.03,
            "cost_flags": {
              "slippage": false,
              "commission": false,
              "swap": false
            }
          }
        },
        {
          "fold_idx": 1,
          "test_window": [
            432.0,
            324.0
          ],
          "embargo_days": 7,
          "train": {
            "trades": 932,
            "wins": 731,
            "pf": 4.59,
            "pnl": 43637.99,
            "wr": 78.4
          },
          "test": {
            "symbol": "GER40.r",
            "trades": 239,
            "wins": 188,
            "pf": 3.86,
            "wr": 78.7,
            "pnl": 3270.11,
            "pnl_gross": 3270.11,
            "commission_usd": 0.0,
            "swap_usd": 0.0,
            "avg_r": 0.9,
            "avg_peak_r": 2.13,
            "avg_giveback": 1.25,
            "dd": 4.4,
            "equity": 4270.11,
            "cost_flags": {
              "slippage": false,
              "commission": false,
              "swap": false
            }
          }
        },
        {
          "fold_idx": 2,
          "test_window": [
            324.0,
            216.0
          ],
          "embargo_days": 7,
          "train": {
            "trades": 967,
            "wins": 764,
            "pf": 3.88,
            "pnl": 119389.23,
            "wr": 79.0
          },
          "test": {
            "symbol": "GER40.r",
            "trades": 199,
            "wins": 141,
            "pf": 2.75,
            "wr": 70.9,
            "pnl": 1352.76,
            "pnl_gross": 1352.76,
            "commission_usd": 0.0,
            "swap_usd": 0.0,
            "avg_r": 0.66,
            "avg_peak_r": 1.83,
            "avg_giveback": 1.18,
            "dd": 6.9,
            "equity": 2352.76,
            "cost_flags": {
              "slippage": false,
              "commission": false,
              "swap": false
            }
          }
        },
        {
          "fold_idx": 3,
          "test_window": [
            216.0,
            108.0
          ],
          "embargo_days": 7,
          "train": {
            "trades": 992,
            "wins": 783,
            "pf": 3.03,
            "pnl": 275535.69,
            "wr": 78.9
          },
          "test": {
            "symbol": "GER40.r",
            "trades": 197,
            "wins": 149,
            "pf": 3.57,
            "wr": 75.6,
            "pnl": 1383.73,
            "pnl_gross": 1383.73,
            "commission_usd": 0.0,
            "swap_usd": 0.0,
            "avg_r": 0.74,
            "avg_peak_r": 1.91,
            "avg_giveback": 1.19,
            "dd": 4.5,
            "equity": 2383.73,
            "cost_flags": {
              "slippage": false,
              "commission": false,
              "swap": false
            }
          }
        },
        {
          "fold_idx": 4,
          "test_window": [
            108.0,
            0.0
          ],
          "embargo_days": 7,
          "train": {
            "trades": 1042,
            "wins": 824,
            "pf": 3.18,
            "pnl": 686497.69,
            "wr": 79.1
          },
          "test": {
            "symbol": "GER40.r",
            "trades": 201,
            "wins": 151,
            "pf": 3.3,
            "wr": 75.1,
            "pnl": 1126.79,
            "pnl_gross": 1126.79,
            "commission_usd": 0.0,
            "swap_usd": 0.0,
            "avg_r": 0.58,
            "avg_peak_r": 1.77,
            "avg_giveback": 1.2,
            "dd": 4.8,
            "equity": 2126.79,
            "cost_flags": {
              "slippage": false,
              "commission": false,
              "swap": false
            }
          }
        }
      ],
      "aggregate": {
        "test_pf_mean": 4.19,
        "test_pf_stdev": 1.68,
        "test_pnl_total": 50133.42,
        "test_pnl_mean": 10026.68,
        "test_trades_total": 1195,
        "n_folds": 5
      }
    },
    "US2000.r": {
      "params": {
        "min_quality": {
          "trending": 40,
          "ranging": 45,
          "volatile": 40,
          "low_vol": 40
        },
        "sl_atr_mult": 1.0,
        "ratchet_1r": 0.2,
        "ratchet_2r": 0.5
      },
      "folds": [
        {
          "fold_idx": 0,
          "test_window": [
            540.0,
            432.0
          ],
          "embargo_days": 7,
          "train": {
            "trades": 157,
            "wins": 101,
            "pf": 2.56,
            "pnl": 929.95,
            "wr": 64.3
          },
          "test": {
            "symbol": "US2000.r",
            "trades": 145,
            "wins": 83,
            "pf": 1.37,
            "wr": 57.2,
            "pnl": 178.85,
            "pnl_gross": 178.85,
            "commission_usd": 0.0,
            "swap_usd": 0.0,
            "avg_r": 0.29,
            "avg_peak_r": 1.4,
            "avg_giveback": 1.14,
            "dd": 8.1,
            "equity": 1179.83,
            "cost_flags": {
              "slippage": false,
              "commission": false,
              "swap": false
            }
          }
        },
        {
          "fold_idx": 1,
          "test_window": [
            432.0,
            324.0
          ],
          "embargo_days": 7,
          "train": {
            "trades": 775,
            "wins": 480,
            "pf": 2.09,
            "pnl": 16629.64,
            "wr": 61.9
          },
          "test": {
            "symbol": "US2000.r",
            "trades": 178,
            "wins": 117,
            "pf": 2.88,
            "wr": 65.7,
            "pnl": 1619.29,
            "pnl_gross": 1619.29,
            "commission_usd": 0.0,
            "swap_usd": 0.0,
            "avg_r": 0.95,
            "avg_peak_r": 1.94,
            "avg_giveback": 0.98,
            "dd": 8.2,
            "equity": 2625.04,
            "cost_flags": {
              "slippage": false,
              "commission": false,
              "swap": false
            }
          }
        },
        {
          "fold_idx": 2,
          "test_window": [
            324.0,
            216.0
          ],
          "embargo_days": 7,
          "train": {
            "trades": 482,
            "wins": 281,
            "pf": 1.87,
            "pnl": 2782.99,
            "wr": 58.3
          },
          "test": {
            "symbol": "US2000.r",
            "trades": 262,
            "wins": 178,
            "pf": 3.19,
            "wr": 67.9,
            "pnl": 2906.76,
            "pnl_gross": 2906.76,
            "commission_usd": 0.0,
            "swap_usd": 0.0,
            "avg_r": 0.89,
            "avg_peak_r": 1.95,
            "avg_giveback": 1.06,
            "dd": 6.3,
            "equity": 3906.76,
            "cost_flags": {
              "slippage": false,
              "commission": false,
              "swap": false
            }
          }
        },
        {
          "fold_idx": 3,
          "test_window": [
            216.0,
            108.0
          ],
          "embargo_days": 7,
          "train": {
            "trades": 190,
            "wins": 103,
            "pf": 1.15,
            "pnl": 91.51,
            "wr": 54.2
          },
          "test": {
            "symbol": "US2000.r",
            "trades": 222,
            "wins": 129,
            "pf": 2.32,
            "wr": 58.1,
            "pnl": 1314.84,
            "pnl_gross": 1314.84,
            "commission_usd": 0.0,
            "swap_usd": 0.0,
            "avg_r": 0.51,
            "avg_peak_r": 1.64,
            "avg_giveback": 1.16,
            "dd": 5.8,
            "equity": 2314.84,
            "cost_flags": {
              "slippage": false,
              "commission": false,
              "swap": false
            }
          }
        },
        {
          "fold_idx": 4,
          "test_window": [
            108.0,
            0.0
          ],
          "embargo_days": 7,
          "train": {
            "trades": 147,
            "wins": 84,
            "pf": 1.36,
            "pnl": 174.32,
            "wr": 57.1
          },
          "test": {
            "symbol": "US2000.r",
            "trades": 83,
            "wins": 48,
            "pf": 1.01,
            "wr": 57.8,
            "pnl": 3.13,
            "pnl_gross": 3.13,
            "commission_usd": 0.0,
            "swap_usd": 0.0,
            "avg_r": 0.07,
            "avg_peak_r": 1.12,
            "avg_giveback": 1.05,
            "dd": 8.7,
            "equity": 1010.54,
            "cost_flags": {
              "slippage": false,
              "commission": false,
              "swap": false
            }
          }
        }
      ],
      "aggregate": {
        "test_pf_mean": 2.15,
        "test_pf_stdev": 0.84,
        "test_pnl_total": 6022.87,
        "test_pnl_mean": 1204.57,
        "test_trades_total": 890,
        "n_folds": 5
      }
    },
    "NAS100.r": {
      "params": {
        "min_quality": {
          "trending": 40,
          "ranging": 45,
          "volatile": 40,
          "low_vol": 40
        },
        "sl_atr_mult": 1.5,
        "ratchet_1r": 0.3,
        "ratchet_2r": 0.7
      },
      "folds": [
        {
          "fold_idx": 0,
          "test_window": [
            540.0,
            432.0
          ],
          "embargo_days": 7,
          "train": {
            "trades": 509,
            "wins": 353,
            "pf": 4.56,
            "pnl": 11731.83,
            "wr": 69.4
          },
          "test": {
            "symbol": "NAS100.r",
            "trades": 221,
            "wins": 166,
            "pf": 3.58,
            "wr": 75.1,
            "pnl": 2768.69,
            "pnl_gross": 2768.69,
            "commission_usd": 0.0,
            "swap_usd": 0.0,
            "avg_r": 0.98,
            "avg_peak_r": 2.09,
            "avg_giveback": 1.12,
            "dd": 6.2,
            "equity": 3768.69,
            "cost_flags": {
              "slippage": false,
              "commission": false,
              "swap": false
            }
          }
        },
        {
          "fold_idx": 1,
          "test_window": [
            432.0,
            324.0
          ],
          "embargo_days": 7,
          "train": {
            "trades": 535,
            "wins": 393,
            "pf": 4.63,
            "pnl": 9056.05,
            "wr": 73.5
          },
          "test": {
            "symbol": "NAS100.r",
            "trades": 142,
            "wins": 92,
            "pf": 2.08,
            "wr": 64.8,
            "pnl": 490.91,
            "pnl_gross": 490.91,
            "commission_usd": 0.0,
            "swap_usd": 0.0,
            "avg_r": 0.47,
            "avg_peak_r": 1.66,
            "avg_giveback": 1.21,
            "dd": 6.2,
            "equity": 1490.91,
            "cost_flags": {
              "slippage": false,
              "commission": false,
              "swap": false
            }
          }
        },
        {
          "fold_idx": 2,
          "test_window": [
            324.0,
            216.0
          ],
          "embargo_days": 7,
          "train": {
            "trades": 328,
            "wins": 245,
            "pf": 4.06,
            "pnl": 5286.19,
            "wr": 74.7
          },
          "test": {
            "symbol": "NAS100.r",
            "trades": 207,
            "wins": 136,
            "pf": 2.3,
            "wr": 65.7,
            "pnl": 828.7,
            "pnl_gross": 828.7,
            "commission_usd": 0.0,
            "swap_usd": 0.0,
            "avg_r": 0.51,
            "avg_peak_r": 1.68,
            "avg_giveback": 1.19,
            "dd": 6.1,
            "equity": 1828.7,
            "cost_flags": {
              "slippage": false,
              "commission": false,
              "swap": false
            }
          }
        },
        {
          "fold_idx": 3,
          "test_window": [
            216.0,
            108.0
          ],
          "embargo_days": 7,
          "train": {
            "trades": 388,
            "wins": 305,
            "pf": 9.01,
            "pnl": 9488.24,
            "wr": 78.6
          },
          "test": {
            "symbol": "NAS100.r",
            "trades": 85,
            "wins": 65,
            "pf": 6.99,
            "wr": 76.5,
            "pnl": 2537.69,
            "pnl_gross": 2537.69,
            "commission_usd": 0.0,
            "swap_usd": 0.0,
            "avg_r": 2.01,
            "avg_peak_r": 2.99,
            "avg_giveback": 0.97,
            "dd": 8.7,
            "equity": 3564.83,
            "cost_flags": {
              "slippage": false,
              "commission": false,
              "swap": false
            }
          }
        },
        {
          "fold_idx": 4,
          "test_window": [
            108.0,
            0.0
          ],
          "embargo_days": 7,
          "train": {
            "trades": 230,
            "wins": 172,
            "pf": 3.22,
            "pnl": 2692.5,
            "wr": 74.8
          },
          "test": {
            "symbol": "NAS100.r",
            "trades": 156,
            "wins": 130,
            "pf": 17.17,
            "wr": 83.3,
            "pnl": 6618.33,
            "pnl_gross": 6618.33,
            "commission_usd": 0.0,
            "swap_usd": 0.0,
            "avg_r": 1.87,
            "avg_peak_r": 2.88,
            "avg_giveback": 1.01,
            "dd": 4.6,
            "equity": 7618.33,
            "cost_flags": {
              "slippage": false,
              "commission": false,
              "swap": false
            }
          }
        }
      ],
      "aggregate": {
        "test_pf_mean": 6.42,
        "test_pf_stdev": 5.65,
        "test_pnl_total": 13244.32,
        "test_pnl_mean": 2648.86,
        "test_trades_total": 811,
        "n_folds": 5
      }
    },
    "USDCAD": {
      "params": {
        "min_quality": {
          "trending": 40,
          "ranging": 45,
          "volatile": 40,
          "low_vol": 40
        },
        "sl_atr_mult": 2.5,
        "ratchet_1r": 0.3,
        "ratchet_2r": 0.7
      },
      "folds": [
        {
          "fold_idx": 0,
          "test_window": [
            540.0,
            432.0
          ],
          "embargo_days": 7,
          "train": {
            "trades": 110,
            "wins": 86,
            "pf": 3.22,
            "pnl": 558.6,
            "wr": 78.2
          },
          "test": {
            "symbol": "USDCAD",
            "trades": 164,
            "wins": 115,
            "pf": 2.87,
            "wr": 70.1,
            "pnl": 1192.45,
            "pnl_gross": 1192.45,
            "commission_usd": 0.0,
            "swap_usd": 0.0,
            "avg_r": 0.78,
            "avg_peak_r": 1.92,
            "avg_giveback": 1.16,
            "dd": 4.5,
            "equity": 2192.45,
            "cost_flags": {
              "slippage": false,
              "commission": false,
              "swap": false
            }
          }
        },
        {
          "fold_idx": 1,
          "test_window": [
            432.0,
            324.0
          ],
          "embargo_days": 7,
          "train": {
            "trades": 732,
            "wins": 536,
            "pf": 2.88,
            "pnl": 10478.21,
            "wr": 73.2
          },
          "test": {
            "symbol": "USDCAD",
            "trades": 106,
            "wins": 76,
            "pf": 2.65,
            "wr": 71.7,
            "pnl": 461.93,
            "pnl_gross": 461.93,
            "commission_usd": 0.0,
            "swap_usd": 0.0,
            "avg_r": 0.58,
            "avg_peak_r": 1.71,
            "avg_giveback": 1.13,
            "dd": 8.4,
            "equity": 1468.6,
            "cost_flags": {
              "slippage": false,
              "commission": false,
              "swap": false
            }
          }
        },
        {
          "fold_idx": 2,
          "test_window": [
            324.0,
            216.0
          ],
          "embargo_days": 7,
          "train": {
            "trades": 632,
            "wins": 453,
            "pf": 2.67,
            "pnl": 4524.46,
            "wr": 71.7
          },
          "test": {
            "symbol": "USDCAD",
            "trades": 187,
            "wins": 148,
            "pf": 5.08,
            "wr": 79.1,
            "pnl": 1520.96,
            "pnl_gross": 1520.96,
            "commission_usd": 0.0,
            "swap_usd": 0.0,
            "avg_r": 0.79,
            "avg_peak_r": 1.97,
            "avg_giveback": 1.19,
            "dd": 6.3,
            "equity": 2520.96,
            "cost_flags": {
              "slippage": false,
              "commission": false,
              "swap": false
            }
          }
        },
        {
          "fold_idx": 3,
          "test_window": [
            216.0,
            108.0
          ],
          "embargo_days": 7,
          "train": {
            "trades": 729,
            "wins": 547,
            "pf": 3.39,
            "pnl": 9610.08,
            "wr": 75.0
          },
          "test": {
            "symbol": "USDCAD",
            "trades": 189,
            "wins": 145,
            "pf": 5.29,
            "wr": 76.7,
            "pnl": 1984.33,
            "pnl_gross": 1984.33,
            "commission_usd": 0.0,
            "swap_usd": 0.0,
            "avg_r": 0.9,
            "avg_peak_r": 2.07,
            "avg_giveback": 1.19,
            "dd": 3.3,
            "equity": 2984.33,
            "cost_flags": {
              "slippage": false,
              "commission": false,
              "swap": false
            }
          }
        },
        {
          "fold_idx": 4,
          "test_window": [
            108.0,
            0.0
          ],
          "embargo_days": 7,
          "train": {
            "trades": 568,
            "wins": 409,
            "pf": 2.73,
            "pnl": 7958.43,
            "wr": 72.0
          },
          "test": {
            "symbol": "USDCAD",
            "trades": 173,
            "wins": 127,
            "pf": 2.64,
            "wr": 73.4,
            "pnl": 640.36,
            "pnl_gross": 640.36,
            "commission_usd": 0.0,
            "swap_usd": 0.0,
            "avg_r": 0.48,
            "avg_peak_r": 1.65,
            "avg_giveback": 1.18,
            "dd": 5.3,
            "equity": 1640.36,
            "cost_flags": {
              "slippage": false,
              "commission": false,
              "swap": false
            }
          }
        }
      ],
      "aggregate": {
        "test_pf_mean": 3.71,
        "test_pf_stdev": 1.21,
        "test_pnl_total": 5800.03,
        "test_pnl_mean": 1160.01,
        "test_trades_total": 819,
        "n_folds": 5
      }
    },
    "SPI200.r": {
      "params": {
        "min_quality": {
          "trending": 40,
          "ranging": 45,
          "volatile": 40,
          "low_vol": 40
        },
        "sl_atr_mult": 1.0,
        "ratchet_1r": 0.2,
        "ratchet_2r": 0.5
      },
      "folds": [
        {
          "fold_idx": 0,
          "test_window": [
            540.0,
            432.0
          ],
          "embargo_days": 7,
          "train": {
            "trades": 243,
            "wins": 143,
            "pf": 1.89,
            "pnl": 1037.02,
            "wr": 58.8
          },
          "test": {
            "symbol": "SPI200.r",
            "trades": 183,
            "wins": 113,
            "pf": 1.81,
            "wr": 61.7,
            "pnl": 413.79,
            "pnl_gross": 413.79,
            "commission_usd": 0.0,
            "swap_usd": 0.0,
            "avg_r": 0.39,
            "avg_peak_r": 1.46,
            "avg_giveback": 1.08,
            "dd": 4.9,
            "equity": 1413.79,
            "cost_flags": {
              "slippage": false,
              "commission": false,
              "swap": false
            }
          }
        },
        {
          "fold_idx": 1,
          "test_window": [
            432.0,
            324.0
          ],
          "embargo_days": 7,
          "train": {
            "trades": 197,
            "wins": 117,
            "pf": 1.71,
            "pnl": 342.56,
            "wr": 59.4
          },
          "test": {
            "symbol": "SPI200.r",
            "trades": 226,
            "wins": 143,
            "pf": 2.43,
            "wr": 63.3,
            "pnl": 1600.26,
            "pnl_gross": 1600.26,
            "commission_usd": 0.0,
            "swap_usd": 0.0,
            "avg_r": 0.57,
            "avg_peak_r": 1.62,
            "avg_giveback": 1.06,
            "dd": 6.9,
            "equity": 2600.26,
            "cost_flags": {
              "slippage": false,
              "commission": false,
              "swap": false
            }
          }
        },
        {
          "fold_idx": 2,
          "test_window": [
            324.0,
            216.0
          ],
          "embargo_days": 7,
          "train": {
            "trades": 523,
            "wins": 323,
            "pf": 2.19,
            "pnl": 2488.69,
            "wr": 61.8
          },
          "test": {
            "symbol": "SPI200.r",
            "trades": 43,
            "wins": 23,
            "pf": 0.61,
            "wr": 53.5,
            "pnl": -51.23,
            "pnl_gross": -51.23,
            "commission_usd": 0.0,
            "swap_usd": 0.0,
            "avg_r": -0.11,
            "avg_peak_r": 0.95,
            "avg_giveback": 1.07,
            "dd": 8.0,
            "equity": 949.09,
            "cost_flags": {
              "slippage": false,
              "commission": false,
              "swap": false
            }
          }
        },
        {
          "fold_idx": 3,
          "test_window": [
            216.0,
            108.0
          ],
          "embargo_days": 7,
          "train": {
            "trades": 544,
            "wins": 319,
            "pf": 1.76,
            "pnl": 1969.82,
            "wr": 58.6
          },
          "test": {
            "symbol": "SPI200.r",
            "trades": 103,
            "wins": 65,
            "pf": 2.35,
            "wr": 63.1,
            "pnl": 431.08,
            "pnl_gross": 431.08,
            "commission_usd": 0.0,
            "swap_usd": 0.0,
            "avg_r": 0.59,
            "avg_peak_r": 1.72,
            "avg_giveback": 1.17,
            "dd": 8.1,
            "equity": 1432.15,
            "cost_flags": {
              "slippage": false,
              "commission": false,
              "swap": false
            }
          }
        },
        {
          "fold_idx": 4,
          "test_window": [
            108.0,
            0.0
          ],
          "embargo_days": 7,
          "train": {
            "trades": 462,
            "wins": 276,
            "pf": 1.82,
            "pnl": 1848.15,
            "wr": 59.7
          },
          "test": {
            "symbol": "SPI200.r",
            "trades": 104,
            "wins": 55,
            "pf": 1.41,
            "wr": 52.9,
            "pnl": 147.38,
            "pnl_gross": 147.38,
            "commission_usd": 0.0,
            "swap_usd": 0.0,
            "avg_r": 0.17,
            "avg_peak_r": 1.37,
            "avg_giveback": 1.27,
            "dd": 8.2,
            "equity": 1149.57,
            "cost_flags": {
              "slippage": false,
              "commission": false,
              "swap": false
            }
          }
        }
      ],
      "aggregate": {
        "test_pf_mean": 1.72,
        "test_pf_stdev": 0.67,
        "test_pnl_total": 2541.28,
        "test_pnl_mean": 508.26,
        "test_trades_total": 659,
        "n_folds": 5
      }
    },
    "EURUSD": {
      "params": {
        "min_quality": {
          "trending": 40,
          "ranging": 45,
          "volatile": 40,
          "low_vol": 40
        },
        "sl_atr_mult": 2.0,
        "ratchet_1r": 0.2,
        "ratchet_2r": 0.5
      },
      "folds": [
        {
          "fold_idx": 0,
          "test_window": [
            540.0,
            432.0
          ],
          "embargo_days": 7,
          "train": {
            "trades": 755,
            "wins": 542,
            "pf": 2.78,
            "pnl": 25511.83,
            "wr": 71.8
          },
          "test": {
            "symbol": "EURUSD",
            "trades": 101,
            "wins": 64,
            "pf": 1.46,
            "wr": 63.4,
            "pnl": 136.5,
            "pnl_gross": 136.5,
            "commission_usd": 0.0,
            "swap_usd": 0.0,
            "avg_r": 0.22,
            "avg_peak_r": 1.46,
            "avg_giveback": 1.27,
            "dd": 8.3,
            "equity": 1139.81,
            "cost_flags": {
              "slippage": false,
              "commission": false,
              "swap": false
            }
          }
        },
        {
          "fold_idx": 1,
          "test_window": [
            432.0,
            324.0
          ],
          "embargo_days": 7,
          "train": {
            "trades": 175,
            "wins": 111,
            "pf": 1.81,
            "pnl": 471.15,
            "wr": 63.4
          },
          "test": {
            "symbol": "EURUSD",
            "trades": 175,
            "wins": 124,
            "pf": 3.28,
            "wr": 70.9,
            "pnl": 1482.91,
            "pnl_gross": 1482.91,
            "commission_usd": 0.0,
            "swap_usd": 0.0,
            "avg_r": 0.87,
            "avg_peak_r": 1.92,
            "avg_giveback": 1.05,
            "dd": 5.6,
            "equity": 2482.91,
            "cost_flags": {
              "slippage": false,
              "commission": false,
              "swap": false
            }
          }
        },
        {
          "fold_idx": 2,
          "test_window": [
            324.0,
            216.0
          ],
          "embargo_days": 7,
          "train": {
            "trades": 459,
            "wins": 314,
            "pf": 2.22,
            "pnl": 2475.53,
            "wr": 68.4
          },
          "test": {
            "symbol": "EURUSD",
            "trades": 71,
            "wins": 42,
            "pf": 1.09,
            "wr": 59.2,
            "pnl": 18.35,
            "pnl_gross": 18.35,
            "commission_usd": 0.0,
            "swap_usd": 0.0,
            "avg_r": 0.06,
            "avg_peak_r": 1.26,
            "avg_giveback": 1.22,
            "dd": 8.6,
            "equity": 1025.24,
            "cost_flags": {
              "slippage": false,
              "commission": false,
              "swap": false
            }
          }
        },
        {
          "fold_idx": 3,
          "test_window": [
            216.0,
            108.0
          ],
          "embargo_days": 7,
          "train": {
            "trades": 272,
            "wins": 187,
            "pf": 1.97,
            "pnl": 829.04,
            "wr": 68.8
          },
          "test": {
            "symbol": "EURUSD",
            "trades": 198,
            "wins": 147,
            "pf": 2.81,
            "wr": 74.2,
            "pnl": 742.57,
            "pnl_gross": 742.57,
            "commission_usd": 0.0,
            "swap_usd": 0.0,
            "avg_r": 0.43,
            "avg_peak_r": 1.54,
            "avg_giveback": 1.11,
            "dd": 7.3,
            "equity": 1742.57,
            "cost_flags": {
              "slippage": false,
              "commission": false,
              "swap": false
            }
          }
        },
        {
          "fold_idx": 4,
          "test_window": [
            108.0,
            0.0
          ],
          "embargo_days": 7,
          "train": {
            "trades": 101,
            "wins": 64,
            "pf": 1.46,
            "pnl": 136.5,
            "wr": 63.4
          },
          "test": {
            "symbol": "EURUSD",
            "trades": 178,
            "wins": 130,
            "pf": 2.4,
            "wr": 73.0,
            "pnl": 792.13,
            "pnl_gross": 792.13,
            "commission_usd": 0.0,
            "swap_usd": 0.0,
            "avg_r": 0.55,
            "avg_peak_r": 1.7,
            "avg_giveback": 1.16,
            "dd": 5.4,
            "equity": 1792.13,
            "cost_flags": {
              "slippage": false,
              "commission": false,
              "swap": false
            }
          }
        }
      ],
      "aggregate": {
        "test_pf_mean": 2.21,
        "test_pf_stdev": 0.82,
        "test_pnl_total": 3172.46,
        "test_pnl_mean": 634.49,
        "test_trades_total": 723,
        "n_folds": 5
      }
    }
  }
}